pystoi/__init__.py
pystoi/stoi.py
pystoi/utils.py
pystoi-0.4.1.dist-info/LICENSE
pystoi-0.4.1.dist-info/METADATA
pystoi-0.4.1.dist-info/WHEEL
pystoi-0.4.1.dist-info/top_level.txt
pystoi-0.4.1.dist-info/RECORD
