Metadata-Version: 2.1
Name: pystoi
Version: 0.4.1
Summary: Computes Short Term Objective Intelligibility measure
Home-page: https://github.com/mpariente/pystoi
Author: Manuel Pariente
Author-email: pariente.mnl@gmail.com
License: MIT
Classifier: Development Status :: 4 - Beta
Classifier: Intended Audience :: Science/Research
Classifier: License :: OSI Approved :: MIT License
Classifier: Programming Language :: Python :: 2
Classifier: Programming Language :: Python :: 2.7
Classifier: Programming Language :: Python :: 3
License-File: LICENSE
